{
    "articles": [
        {
            "author": "MARCIA DUNN",
            "content": "CAPE CANAVERAL, Fla. (AP) — A galactic photo shoot has captured more than 3 billion stars and galaxies in one of the biggest sky surveys ever. A dark-energy camera on a telescope in Chile made the ob… [+1326 chars]",
            "description": "CAPE CANAVERAL, Fla. (AP) — A galactic photo shoot has captured more than 3 billion stars and galaxies in one of the biggest sky surveys ever. A dark-energy camera on a telescope in Chile made the observations over two years, focusing on the Southern Hemisphe…",
            "publishedAt": "2023-01-19T17:07:33Z",
            "source": {
                "id": "associated-press",
                "name": "Associated Press"
            },
            "title": "Say cheese! Galactic photo shoot captures 3 billion stars",
            "url": "https://apnews.com/60fecb7e18e0ad9b247b8d7aa75a4b3c",
            "urlToImage": "https://storage.googleapis.com/afs-prod/media/9112f60b2dc84c849daffb17f6015f18/3000.jpeg"
        },
        {
            "author": "JIM SALTER",
            "content": "ST. LOUIS (AP) — A group of religious leaders who support abortion rights filed a lawsuit on Thursday challenging Missouri's law that bans abortions in nearly all cases, saying lawmakers openly invok… [+3946 chars]",
            "description": "ST. LOUIS (AP) — A group of religious leaders who support abortion rights filed a lawsuit on Thursday challenging Missouri's law that bans abortions in nearly all cases, saying lawmakers openly invoked their religious beliefs while drafting the measure and th…",
            "publishedAt": "2023-01-19T16:27:55Z",
            "source": {
                "id": "associated-press",
                "name": "Associated Press"
            },
            "title": "Religious leaders sue to block Missouri's abortion ban",
            "url": "https://apnews.com/05d21a1234877ffcd358ad74bebe4472",
            "urlToImage": "https://storage.googleapis.com/afs-prod/media/6d3f0d93acf246f88afb526cf79b64f7/3000.jpeg"
        },
        {
            "author": "MORGAN LEE",
            "content": "SANTA FE, N.M. (AP) — Actor Alec Baldwin and a weapons specialist will be charged with involuntary manslaughter in the fatal shooting of a cinematographer who was killed on a New Mexico movie set, pr… [+5873 chars]",
            "description": "SANTA FE, N.M. (AP) — Actor Alec Baldwin and a weapons specialist will be charged with involuntary manslaughter in the fatal shooting of a cinematographer who was killed on a New Mexico movie set, prosecutors announced Thursday, citing a “criminal disregard f…",
            "publishedAt": "2023-01-19T15:37:02Z",
            "source": {
                "id": "associated-press",
                "name": "Associated Press"
            },
            "title": "Alec Baldwin to be charged with manslaughter in set shooting",
            "url": "https://apnews.com/8c76eddb8a6418419078903d24ec3813",
            "urlToImage": "https://storage.googleapis.com/afs-prod/media/5953a6c5ecaf4402840f084af3fc44dd/3000.jpeg"
        },
        {
            "author": "FABIANO MAISONNAVE, TATIANA POLLASTRI AND ERALDO PERES",
            "content": "XAPURI, Brazil (AP) — Rubber tapper Raimundo Mendes de Barros prepares to leave his home, surrounded by rainforest, for an errand in the Brazilian Amazon city of Xapuri. He slides his long, scarred, … [+6704 chars]",
            "description": "XAPURI, Brazil (AP) — Rubber tapper Raimundo Mendes de Barros prepares to leave his home, surrounded by rainforest, for an errand in the Brazilian Amazon city of Xapuri. He slides his long, scarred, 77-year-old feet into a pair of sneakers made by Veja, a Fre…",
            "publishedAt": "2023-01-19T13:03:16Z",
            "source": {
                "id": "associated-press",
                "name": "Associated Press"
            },
            "title": "Fashion sneakers propel sustainable rubber in Brazil Amazon",
            "url": "https://apnews.com/68d33094e142db88f5b00f8384f5a18f",
            "urlToImage": "https://storage.googleapis.com/afs-prod/media/b50e60aea15b4d3593619441472be4f2/3000.jpeg"
        },
        {
            "author": "SALLY HO, ANGELIKI KASTANIS and LINDSEY BAHR",
            "content": "With hundreds of new movies released each year, many of us depend on the expertise of film critics to help curate our own watching — a thoroughly communal yet deeply personal experience.To honor the … [+5571 chars]",
            "description": "With hundreds of new movies released each year, many of us depend on the expertise of film critics to help curate our own watching — a thoroughly communal yet deeply personal experience.",
            "publishedAt": "2023-01-19T13:01:50Z",
            "source": {
                "id": "associated-press",
                "name": "Associated Press"
            },
            "title": "AP Top 25 Movies, ranking 2022's best: What made the cut?",
            "url": "https://apnews.com/325b1c1493a5a95f5cb94ce577612cb6",
            "urlToImage": "https://storage.googleapis.com/afs-prod/media/8be42517d97541a492192a009efa656d/1920.jpeg"
        },
        {
            "author": "JOSH DUBOW",
            "content": "SANTA CLARA, Calif. (AP) — For Kyle Shanahan, the chance to coach the San Francisco 49ers against the Dallas Cowboys in a playoff game is a throwback to when that rivalry was the biggest in football.… [+6281 chars]",
            "description": "SANTA CLARA, Calif. (AP) — For Kyle Shanahan, the chance to coach the San Francisco 49ers against the Dallas Cowboys in a playoff game is a throwback to when that rivalry was the biggest in football.",
            "publishedAt": "2023-01-19T11:00:28Z",
            "source": {
                "id": "associated-press",
                "name": "Associated Press"
            },
            "title": "Cowboys-49ers rivalry set for record-tying 9th playoff game",
            "url": "https://apnews.com/083928bbc0f793885f2eb89bb7ef771d",
            "urlToImage": "https://storage.googleapis.com/afs-prod/media/b5863a7e241b4de88fbf05b21ea7f45f/1960.jpeg"
        },
        {
            "author": "GEIR MOULSON and JAMEY KEATEN",
            "content": "BERLIN (AP) — Germany faced mounting pressure to supply battle tanks to Kyiv and Ukrainian President Volodymyr Zelenskyy aired frustration about not obtaining enough weaponry as Western allies confer… [+5681 chars]",
            "description": "BERLIN (AP) — Germany faced mounting pressure to supply battle tanks to Kyiv and Ukrainian President Volodymyr Zelenskyy aired frustration about not obtaining enough weaponry as Western allies conferred Thursday on how best to support Ukraine nearly 11 months…",
            "publishedAt": "2023-01-19T09:48:42Z",
            "source": {
                "id": "associated-press",
                "name": "Associated Press"
            },
            "title": "Germany pressed on tanks for Ukraine; Kyiv airs frustration",
            "url": "https://apnews.com/1cf2593806068a08ab63e78ddd681999",
            "urlToImage": "https://storage.googleapis.com/afs-prod/media/45c3484295914a68bd7615bc446b947c/3000.jpeg"
        },
        {
            "author": "NICK PERRY",
            "content": "WELLINGTON, New Zealand (AP) — New Zealand Prime Minister Jacinda Ardern, who became a global icon of the left and exemplified a new style of leadership, said Thursday that she would leave office.Jus… [+7946 chars]",
            "description": "WELLINGTON, New Zealand (AP) — New Zealand Prime Minister Jacinda Ardern, who became a global icon of the left and exemplified a new style of leadership, said Thursday that she would leave office.",
            "publishedAt": "2023-01-19T06:51:06Z",
            "source": {
                "id": "associated-press",
                "name": "Associated Press"
            },
            "title": "New Zealand's Jacinda Ardern, an icon to many, to step down",
            "url": "https://apnews.com/0e6d8eedd96f94aab07eeb0c37164591",
            "urlToImage": "https://storage.googleapis.com/afs-prod/media/f64c08ef6569448db7fd84fb4b32a6ab/3000.jpeg"
        },
        {
            "author": "DANIEL POLITI and FRANKLIN BRICEÑO",
            "content": "LIMA, Peru (AP) — People poured into Peru's coastal capital, many from remote Andean regions, for a protest Thursday against President Dina Boluarte and in support of her predecessor, whose ouster la… [+6530 chars]",
            "description": "LIMA, Peru (AP) — People poured into Peru's coastal capital, many from remote Andean regions, for a protest Thursday against President Dina Boluarte and in support of her predecessor, whose ouster last month launched deadly unrest and cast the nation into pol…",
            "publishedAt": "2023-01-19T05:05:05Z",
            "source": {
                "id": "associated-press",
                "name": "Associated Press"
            },
            "title": "Peru’s Andes ‘descended' on capital to demand leader resign",
            "url": "https://apnews.com/abc5c843f4ef886efff634fce2576abe",
            "urlToImage": "https://storage.googleapis.com/afs-prod/media/23060280c3064b73a681b0367b7ba006/3000.jpeg"
        },
        {
            "author": "JOSH BOAK",
            "content": "WASHINGTON (AP) — The countdown toward a possible U.S. government default began Thursday with the Treasury Department implementing accounting measures as a stopgap, while friction between President J… [+6877 chars]",
            "description": "WASHINGTON (AP) — The countdown toward a possible U.S.",
            "publishedAt": "2023-01-19T05:04:40Z",
            "source": {
                "id": "associated-press",
                "name": "Associated Press"
            },
            "title": "US Treasury buys time for Biden and GOP on debt limit deal",
            "url": "https://apnews.com/3652d50a1567c1e7ab544614b7f2b357",
            "urlToImage": "https://storage.googleapis.com/afs-prod/media/3fbd0ce3f7ec45bab754f3ee93002eb2/3000.jpeg"
        }
    ],
    "status": "ok",
    "totalResults": 10
}